plain/models/AGENTS.md
plain/models/CHANGELOG.md
plain/models/README.md
plain/models/__init__.py
plain/models/aggregates.py
plain/models/base.py
plain/models/config.py
plain/models/connections.py
plain/models/constants.py
plain/models/constraints.py
plain/models/database_url.py
plain/models/db.py
plain/models/default_settings.py
plain/models/deletion.py
plain/models/entrypoints.py
plain/models/enums.py
plain/models/exceptions.py
plain/models/expressions.py
plain/models/forms.py
plain/models/indexes.py
plain/models/lookups.py
plain/models/meta.py
plain/models/options.py
plain/models/otel.py
plain/models/preflight.py
plain/models/query.py
plain/models/query_utils.py
plain/models/registry.py
plain/models/transaction.py
plain/models/types.py
plain/models/types.pyi
plain/models/utils.py
plain/models/backends/__init__.py
plain/models/backends/ddl_references.py
plain/models/backends/guards.py
plain/models/backends/utils.py
plain/models/backends/base/__init__.py
plain/models/backends/base/base.py
plain/models/backends/base/client.py
plain/models/backends/base/creation.py
plain/models/backends/base/features.py
plain/models/backends/base/introspection.py
plain/models/backends/base/operations.py
plain/models/backends/base/schema.py
plain/models/backends/base/validation.py
plain/models/backends/mysql/__init__.py
plain/models/backends/mysql/base.py
plain/models/backends/mysql/client.py
plain/models/backends/mysql/compiler.py
plain/models/backends/mysql/creation.py
plain/models/backends/mysql/features.py
plain/models/backends/mysql/introspection.py
plain/models/backends/mysql/operations.py
plain/models/backends/mysql/schema.py
plain/models/backends/mysql/validation.py
plain/models/backends/postgresql/__init__.py
plain/models/backends/postgresql/base.py
plain/models/backends/postgresql/client.py
plain/models/backends/postgresql/creation.py
plain/models/backends/postgresql/features.py
plain/models/backends/postgresql/introspection.py
plain/models/backends/postgresql/operations.py
plain_models-0.70.0.dist-info/METADATA
plain_models-0.70.0.dist-info/WHEEL
plain_models-0.70.0.dist-info/entry_points.txt
plain_models-0.70.0.dist-info/licenses/LICENSE
plain_models-0.70.0.dist-info/RECORD
