Metadata-Version: 2.4
Name: plain.models
Version: 0.70.0
Summary: Model your data and store it in a database.
Author-email: Dave Gaeddert <dave.gaeddert@dropseed.dev>
License-Expression: BSD-3-Clause
License-File: LICENSE
Requires-Python: >=3.13
Requires-Dist: plain<1.0.0
Requires-Dist: sqlparse>=0.3.1
